<VideoStream timebaseNumerator="1" timebaseDenomenator="1000">
<Group pts="0" duration="9799" size="4651829" />
<Group pts="9968" duration="9840" size="4267786" />
<Group pts="19978" duration="7913" size="2420971" />
<Group pts="28028" duration="9840" size="2681095" />
<Group pts="38038" duration="9840" size="2526814" />
<Group pts="48048" duration="9840" size="4068521" />
<Group pts="58058" duration="9840" size="3784434" />
<Group pts="68068" duration="9840" size="1238866" />
<Group pts="78078" duration="9799" size="1296511" />
<Group pts="88046" duration="9799" size="3033866" />
<Group pts="98015" duration="9799" size="3735308" />
<Group pts="107983" duration="6273" size="2518473" />
<Group pts="114364" duration="9840" size="3248990" />
<Group pts="124374" duration="9840" size="3381366" />
<Group pts="134384" duration="9799" size="3511582" />
<Group pts="144353" duration="1107" size="268116" />
<Group pts="145479" duration="5084" size="157825" />
<Group pts="150651" duration="9799" size="1359424" />
<Group pts="160619" duration="8077" size="5437318" />
<Group pts="168835" duration="9799" size="3164469" />
<Group pts="178804" duration="7503" size="6124562" />
<Group pts="186436" duration="2952" size="122751" />
<Group pts="189439" duration="7913" size="345158" />
<Group pts="197489" duration="2337" size="86716" />
<Group pts="199866" duration="2419" size="121730" />
<Group pts="202327" duration="5699" size="220865" />
<Group pts="208125" duration="5084" size="162199" />
<Group pts="213296" duration="5412" size="209397" />
<Group pts="218802" duration="3116" size="103143" />
<Group pts="221972" duration="9799" size="2454364" />
<Group pts="231940" duration="9758" size="5290946" />
<Group pts="241867" duration="9799" size="6002855" />
<Group pts="251835" duration="9799" size="5957218" />
<Group pts="261803" duration="9799" size="5927306" />
<Group pts="271772" duration="9799" size="6665421" />
<Group pts="281740" duration="9840" size="6359412" />
<Group pts="291750" duration="9840" size="5071154" />
<Group pts="301760" duration="9799" size="4791226" />
<Group pts="311728" duration="3608" size="1924589" />
<Group pts="315398" duration="9799" size="4305872" />
<Group pts="325367" duration="9799" size="5554420" />
<Group pts="335335" duration="4428" size="3669045" />
<Group pts="339840" duration="9799" size="7655976" />
<Group pts="349808" duration="9799" size="6878085" />
<Group pts="359776" duration="5904" size="3952100" />
<Group pts="365782" duration="9799" size="5278038" />
<Group pts="375750" duration="1927" size="1246676" />
<Group pts="377711" duration="2993" size="1692878" />
<Group pts="380755" duration="6478" size="3921828" />
<Group pts="387345" duration="9840" size="4054915" />
<Group pts="397355" duration="9840" size="5836791" />
<Group pts="407365" duration="9799" size="5495407" />
<Group pts="417334" duration="9799" size="5692825" />
<Group pts="427302" duration="9799" size="5565355" />
<Group pts="437270" duration="9799" size="5808210" />
<Group pts="447238" duration="9799" size="5732631" />
<Group pts="457207" duration="9799" size="4875222" />
<Group pts="467175" duration="9799" size="4670165" />
<Group pts="477143" duration="9799" size="4679568" />
<Group pts="487112" duration="1312" size="667137" />
<Group pts="488446" duration="9799" size="4148647" />
<Group pts="498415" duration="9799" size="4147976" />
<Group pts="508383" duration="9799" size="3660891" />
<Group pts="518351" duration="9799" size="4021988" />
<Group pts="528319" duration="1148" size="596526" />
<Group pts="529487" duration="9799" size="4511153" />
<Group pts="539456" duration="9799" size="4767934" />
<Group pts="549424" duration="9799" size="5299747" />
<Group pts="559392" duration="9799" size="5131093" />
<Group pts="569360" duration="3239" size="1703493" />
<Group pts="572655" duration="9840" size="4796302" />
<Group pts="582665" duration="9799" size="4297286" />
<Group pts="592634" duration="9799" size="3360918" />
<Group pts="602602" duration="9799" size="3588143" />
<Group pts="612570" duration="9799" size="4345543" />
<Group pts="622539" duration="9799" size="5256162" />
<Group pts="632507" duration="3731" size="2143366" />
<Group pts="636302" duration="9348" size="5457752" />
<Group pts="645812" duration="9799" size="5839857" />
<Group pts="655780" duration="9799" size="5895849" />
<Group pts="665748" duration="6888" size="4337995" />
<Group pts="672755" duration="9717" size="5753468" />
<Group pts="682640" duration="9799" size="5308568" />
<Group pts="692609" duration="9799" size="5766936" />
<Group pts="702577" duration="1927" size="1149788" />
<Group pts="704537" duration="3444" size="2068975" />
<Group pts="708041" duration="9799" size="5336838" />
<Group pts="718009" duration="9799" size="6189721" />
<Group pts="727977" duration="9758" size="7045417" />
<Group pts="737904" duration="9840" size="6907918" />
<Group pts="747914" duration="9799" size="6181465" />
<Group pts="757882" duration="4059" size="2147514" />
<Group pts="762011" duration="3485" size="1857430" />
<Group pts="765556" duration="5494" size="2551951" />
<Group pts="771145" duration="9799" size="4917273" />
<Group pts="781114" duration="2091" size="1007695" />
<Group pts="783241" duration="9799" size="4881988" />
<Group pts="793209" duration="1886" size="915061" />
<Group pts="795128" duration="9799" size="5389478" />
<Group pts="805096" duration="2788" size="1733578" />
<Group pts="807932" duration="9799" size="5240880" />
<Group pts="817900" duration="4182" size="2440946" />
<Group pts="822155" duration="1804" size="995814" />
<Group pts="823990" duration="9799" size="4953943" />
<Group pts="833958" duration="9799" size="5724458" />
<Group pts="843926" duration="9799" size="6378841" />
<Group pts="853895" duration="9799" size="6313651" />
<Group pts="863863" duration="9799" size="5956202" />
<Group pts="873831" duration="9799" size="5759863" />
<Group pts="883800" duration="9799" size="5432040" />
<Group pts="893768" duration="9799" size="5001490" />
<Group pts="903736" duration="9840" size="5293433" />
<Group pts="913746" duration="9799" size="4701882" />
<Group pts="923714" duration="1968" size="876955" />
<Group pts="925716" duration="9840" size="4367777" />
<Group pts="935726" duration="9799" size="4478784" />
<Group pts="945695" duration="2296" size="1187455" />
<Group pts="948030" duration="9799" size="4817022" />
<Group pts="957999" duration="9799" size="5333082" />
<Group pts="967967" duration="9799" size="6189019" />
<Group pts="977935" duration="9840" size="5849188" />
<Group pts="987945" duration="7954" size="4236830" />
<Group pts="996037" duration="9799" size="5032313" />
<Group pts="1006005" duration="9840" size="4781678" />
<Group pts="1016015" duration="1927" size="978392" />
<Group pts="1017975" duration="9799" size="5205448" />
<Group pts="1027944" duration="2009" size="1170169" />
<Group pts="1029987" duration="9799" size="5524404" />
<Group pts="1039956" duration="2091" size="1280608" />
<Group pts="1042083" duration="4387" size="2120793" />
<Group pts="1046546" duration="3813" size="1929626" />
<Group pts="1050424" duration="9840" size="5535512" />
<Group pts="1060434" duration="9840" size="5055707" />
<Group pts="1070444" duration="9840" size="3387169" />
<Group pts="1080454" duration="9840" size="2788955" />
<Group pts="1090464" duration="9840" size="3512710" />
<Group pts="1100474" duration="9840" size="2857425" />
<Group pts="1110484" duration="9840" size="2734335" />
<Group pts="1120494" duration="1394" size="451163" />
<Group pts="1121912" duration="9840" size="2612195" />
<Group pts="1131922" duration="1025" size="339540" />
<Group pts="1132965" duration="1804" size="574818" />
<Group pts="1134800" duration="3936" size="1081821" />
<Group pts="1138804" duration="9840" size="3145991" />
<Group pts="1148814" duration="9840" size="2879788" />
<Group pts="1158824" duration="9840" size="2547592" />
<Group pts="1168834" duration="9799" size="4136197" />
<Group pts="1178803" duration="6601" size="3890285" />
<Group pts="1185518" duration="7544" size="4083637" />
<Group pts="1193192" duration="3116" size="1912092" />
<Group pts="1196362" duration="9840" size="6029299" />
<Group pts="1206372" duration="1845" size="1139833" />
<Group pts="1208249" duration="9840" size="6405947" />
<Group pts="1218259" duration="2624" size="1773692" />
<Group pts="1220928" duration="6478" size="4598547" />
<Group pts="1227518" duration="9799" size="5677294" />
<Group pts="1237486" duration="9799" size="4907441" />
<Group pts="1247455" duration="4141" size="2199379" />
<Group pts="1251667" duration="9799" size="5195673" />
<Group pts="1261635" duration="2665" size="1484829" />
<Group pts="1264346" duration="9799" size="5408943" />
<Group pts="1274315" duration="9840" size="5775701" />
<Group pts="1284325" duration="9840" size="5690629" />
<Group pts="1294335" duration="3321" size="1862643" />
<Group pts="1297713" duration="9799" size="5213395" />
<Group pts="1307681" duration="9840" size="5304296" />
<Group pts="1317691" duration="9840" size="5085317" />
<Group pts="1327701" duration="7708" size="3792979" />
<Group pts="1335543" duration="4469" size="2223047" />
<Group pts="1340089" duration="3280" size="1452995" />
<Group pts="1343425" duration="4838" size="2266193" />
<Group pts="1348347" duration="5371" size="2391045" />
<Group pts="1353811" duration="9840" size="4365715" />
<Group pts="1363821" duration="1640" size="761988" />
<Group pts="1365489" duration="5494" size="2450185" />
<Group pts="1371078" duration="9840" size="4958105" />
<Group pts="1381088" duration="9840" size="5030975" />
<Group pts="1391098" duration="9799" size="5509332" />
<Group pts="1401066" duration="9840" size="5428158" />
<Group pts="1411076" duration="9840" size="5570650" />
<Group pts="1421086" duration="1107" size="642244" />
<Group pts="1422212" duration="6191" size="2639212" />
<Group pts="1428510" duration="7872" size="3263697" />
<Group pts="1436518" duration="9840" size="3914560" />
<Group pts="1446528" duration="9840" size="3560601" />
<Group pts="1456538" duration="9840" size="4386782" />
<Group pts="1466548" duration="5125" size="2353240" />
<Group pts="1471762" duration="9840" size="3999784" />
<Group pts="1481772" duration="5248" size="2504934" />
<Group pts="1487111" duration="8282" size="3548503" />
<Group pts="1495536" duration="9799" size="5011790" />
<Group pts="1505504" duration="9840" size="5511943" />
<Group pts="1515514" duration="9799" size="5897957" />
<Group pts="1525482" duration="9799" size="6593470" />
<Group pts="1535451" duration="9799" size="6257503" />
<Group pts="1545419" duration="9840" size="6235249" />
<Group pts="1555429" duration="2501" size="1600964" />
<Group pts="1557973" duration="9799" size="5677140" />
<Group pts="1567941" duration="2911" size="1829104" />
<Group pts="1570903" duration="9799" size="5547505" />
<Group pts="1580871" duration="6191" size="3708852" />
<Group pts="1587169" duration="9840" size="5440221" />
<Group pts="1597179" duration="9840" size="5308678" />
<Group pts="1607189" duration="2993" size="1729804" />
<Group pts="1610234" duration="9840" size="5783942" />
<Group pts="1620244" duration="9840" size="5847015" />
<Group pts="1630254" duration="9799" size="5955380" />
<Group pts="1640222" duration="9799" size="6531064" />
<Group pts="1650190" duration="9799" size="6586804" />
<Group pts="1660159" duration="9840" size="6399480" />
<Group pts="1670169" duration="9799" size="5603956" />
<Group pts="1680137" duration="9799" size="5209887" />
<Group pts="1690105" duration="9840" size="5209623" />
<Group pts="1700115" duration="9799" size="5089307" />
<Group pts="1710083" duration="6191" size="3198469" />
<Group pts="1716381" duration="9799" size="5427681" />
<Group pts="1726350" duration="9635" size="5119273" />
<Group pts="1736151" duration="9840" size="6032901" />
<Group pts="1746161" duration="9799" size="4688601" />
<Group pts="1756129" duration="9840" size="3443578" />
<Group pts="1766139" duration="9840" size="3138316" />
<Group pts="1776149" duration="9799" size="2273235" />
<Group pts="1786118" duration="9799" size="3407870" />
<Group pts="1796086" duration="9799" size="5463512" />
<Group pts="1806054" duration="9799" size="6268999" />
<Group pts="1816023" duration="9799" size="6469762" />
<Group pts="1825991" duration="9799" size="6585118" />
<Group pts="1835959" duration="9799" size="7233689" />
<Group pts="1845927" duration="9799" size="7431288" />
<Group pts="1855896" duration="9799" size="6453273" />
<Group pts="1865864" duration="9799" size="5600392" />
<Group pts="1875832" duration="9799" size="5512896" />
<Group pts="1885801" duration="9799" size="5092350" />
<Group pts="1895769" duration="9799" size="5126402" />
<Group pts="1905737" duration="9799" size="5129995" />
<Group pts="1915705" duration="9799" size="4926115" />
<Group pts="1925674" duration="9799" size="5079365" />
<Group pts="1935642" duration="1722" size="894774" />
<Group pts="1937394" duration="9799" size="5005849" />
<Group pts="1947362" duration="9799" size="5043238" />
<Group pts="1957330" duration="3321" size="1651985" />
<Group pts="1960709" duration="9799" size="4955474" />
<Group pts="1970677" duration="9799" size="4704016" />
<Group pts="1980645" duration="9799" size="4633755" />
<Group pts="1990614" duration="9799" size="4617312" />
<Group pts="2000582" duration="9799" size="4649113" />
<Group pts="2010550" duration="9799" size="3868762" />
<Group pts="2020519" duration="9799" size="4792551" />
<Group pts="2030487" duration="9799" size="4408369" />
<Group pts="2040455" duration="2296" size="1147740" />
<Group pts="2042791" duration="9799" size="4791385" />
<Group pts="2052759" duration="1066" size="567225" />
<Group pts="2053843" duration="9799" size="4834829" />
<Group pts="2063812" duration="6560" size="3081086" />
<Group pts="2070485" duration="9799" size="4210674" />
<Group pts="2080453" duration="2501" size="1144175" />
<Group pts="2082998" duration="9799" size="4326472" />
<Group pts="2092966" duration="9799" size="4601881" />
<Group pts="2102934" duration="9840" size="4649529" />
<Group pts="2112944" duration="9840" size="5212907" />
<Group pts="2122954" duration="1394" size="807960" />
<Group pts="2124372" duration="5289" size="2732508" />
<Group pts="2129753" duration="9799" size="4656775" />
<Group pts="2139721" duration="3239" size="1663080" />
<Group pts="2143016" duration="8118" size="3940569" />
<Group pts="2151274" duration="9799" size="4756273" />
<Group pts="2161242" duration="9799" size="4803126" />
<Group pts="2171211" duration="4633" size="2036673" />
<Group pts="2175924" duration="6519" size="3331159" />
<Group pts="2182555" duration="9799" size="4830859" />
<Group pts="2192524" duration="9840" size="4319800" />
<Group pts="2202534" duration="9799" size="4475753" />
<Group pts="2212502" duration="2132" size="1144610" />
<Group pts="2214671" duration="3485" size="1875505" />
<Group pts="2218216" duration="2706" size="1379090" />
<Group pts="2220969" duration="9840" size="4117849" />
<Group pts="2230979" duration="9799" size="4525170" />
<Group pts="2240947" duration="9840" size="4691430" />
<Group pts="2250957" duration="9840" size="4206253" />
<Group pts="2260967" duration="9840" size="4395268" />
<Group pts="2270977" duration="4879" size="2432273" />
<Group pts="2275940" duration="5494" size="2289311" />
<Group pts="2281529" duration="9758" size="4583003" />
<Group pts="2291456" duration="5002" size="2398049" />
<Group pts="2296544" duration="9840" size="4346793" />
<Group pts="2306554" duration="1968" size="918189" />
<Group pts="2308556" duration="4264" size="2149179" />
<Group pts="2312894" duration="9840" size="4233888" />
<Group pts="2322904" duration="9840" size="4386324" />
<Group pts="2332914" duration="9799" size="4851197" />
<Group pts="2342882" duration="9799" size="4598690" />
<Group pts="2352851" duration="9799" size="4801834" />
<Group pts="2362819" duration="1025" size="545142" />
<Group pts="2363862" duration="9799" size="4536257" />
<Group pts="2373830" duration="4510" size="2191111" />
<Group pts="2378418" duration="3936" size="1990643" />
<Group pts="2382422" duration="9799" size="4850541" />
<Group pts="2392390" duration="4141" size="2098108" />
<Group pts="2396603" duration="9840" size="4408798" />
<Group pts="2406613" duration="9840" size="4511533" />
<Group pts="2416623" duration="8610" size="4055681" />
<Group pts="2425381" duration="9840" size="3435252" />
<Group pts="2435391" duration="9840" size="3275612" />
<Group pts="2445401" duration="3444" size="1218994" />
<Group pts="2448905" duration="9840" size="3194888" />
<Group pts="2458915" duration="1763" size="692514" />
<Group pts="2460708" duration="9758" size="3662605" />
<Group pts="2470635" duration="9799" size="4934672" />
<Group pts="2480603" duration="9799" size="5813999" />
<Group pts="2490571" duration="9799" size="6533945" />
<Group pts="2500540" duration="9799" size="6499894" />
<Group pts="2510508" duration="9799" size="6707450" />
<Group pts="2520476" duration="1968" size="1439591" />
<Group pts="2522478" duration="9799" size="6857125" />
<Group pts="2532447" duration="9799" size="7256242" />
<Group pts="2542415" duration="9799" size="6908707" />
<Group pts="2552383" duration="9799" size="7257769" />
<Group pts="2562351" duration="9840" size="7798212" />
<Group pts="2572361" duration="9799" size="7101145" />
<Group pts="2582330" duration="9799" size="6260092" />
<Group pts="2592298" duration="9799" size="5874773" />
<Group pts="2602266" duration="9799" size="5509658" />
<Group pts="2612235" duration="9799" size="4915626" />
<Group pts="2622203" duration="9799" size="6095567" />
<Group pts="2632171" duration="9799" size="6899363" />
<Group pts="2642140" duration="9799" size="6398781" />
<Group pts="2652108" duration="9799" size="6083521" />
<Group pts="2662076" duration="9799" size="5697438" />
<Group pts="2672044" duration="9840" size="4820846" />
<Group pts="2682054" duration="4346" size="1809076" />
<Group pts="2686475" duration="9840" size="3932278" />
<Group pts="2696485" duration="2091" size="807242" />
<Group pts="2698613" duration="9840" size="3768859" />
<Group pts="2708623" duration="5002" size="1759988" />
<Group pts="2713711" duration="9840" size="2814916" />
<Group pts="2723721" duration="5576" size="1452824" />
<Group pts="2729393" duration="9840" size="2726943" />
<Group pts="2739403" duration="1763" size="532341" />
<Group pts="2741197" duration="9840" size="2454501" />
<Group pts="2751207" duration="984" size="280735" />
<Group pts="2752208" duration="9840" size="2560559" />
<Group pts="2762218" duration="6560" size="1641703" />
<Group pts="2768891" duration="9840" size="2810903" />
<Group pts="2778901" duration="4879" size="1467961" />
<Group pts="2783864" duration="5166" size="1387607" />
<Group pts="2789120" duration="9799" size="3664253" />
<Group pts="2799088" duration="9840" size="3678179" />
<Group pts="2809098" duration="4264" size="1390701" />
<Group pts="2813436" duration="4961" size="1455363" />
<Group pts="2818482" duration="4879" size="1328037" />
<Group pts="2823446" duration="5412" size="1412281" />
<Group pts="2828951" duration="5740" size="1415277" />
<Group pts="2834790" duration="5412" size="1467349" />
<Group pts="2840296" duration="3526" size="949172" />
<Group pts="2843883" duration="3362" size="999241" />
<Group pts="2847303" duration="9840" size="3075803" />
<Group pts="2857313" duration="1353" size="426962" />
<Group pts="2858689" duration="9840" size="2954286" />
<Group pts="2868699" duration="7093" size="2093614" />
<Group pts="2875915" duration="9840" size="2358558" />
<Group pts="2885925" duration="6314" size="1567053" />
<Group pts="2892348" duration="9840" size="4418760" />
<Group pts="2902358" duration="9799" size="5990124" />
<Group pts="2912326" duration="9799" size="6130219" />
<Group pts="2922294" duration="9799" size="6528985" />
<Group pts="2932263" duration="9840" size="6622660" />
<Group pts="2942273" duration="9799" size="6491766" />
<Group pts="2952241" duration="9799" size="7528880" />
<Group pts="2962209" duration="9020" size="7622086" />
<Group pts="2971385" duration="9840" size="7037708" />
<Group pts="2981395" duration="9799" size="7047429" />
<Group pts="2991363" duration="1763" size="1418651" />
<Group pts="2993157" duration="4141" size="1871940" />
<Group pts="2997369" duration="3567" size="2520951" />
<Group pts="3000998" duration="2501" size="1091201" />
<Group pts="3003542" duration="2870" size="1970630" />
<Group pts="3006462" duration="9799" size="4136013" />
<Group pts="3016430" duration="1271" size="871015" />
<Group pts="3017723" duration="9799" size="5091565" />
<Group pts="3027691" duration="4223" size="2561117" />
<Group pts="3031987" duration="9799" size="4811869" />
<Group pts="3041956" duration="9799" size="5561546" />
<Group pts="3051924" duration="9799" size="4830363" />
<Group pts="3061892" duration="9799" size="5229431" />
<Group pts="3071860" duration="4674" size="2480046" />
<Group pts="3076615" duration="9840" size="4756184" />
<Group pts="3086625" duration="9799" size="4679533" />
<Group pts="3096594" duration="9799" size="4313988" />
<Group pts="3106562" duration="9799" size="6424658" />
<Group pts="3116530" duration="6601" size="4700601" />
<Group pts="3123245" duration="9840" size="5373043" />
<Group pts="3133255" duration="9840" size="5376379" />
<Group pts="3143265" duration="9840" size="5152805" />
<Group pts="3153275" duration="3116" size="1784442" />
<Group pts="3156445" duration="9840" size="4980864" />
<Group pts="3166455" duration="9799" size="4974355" />
<Group pts="3176423" duration="9799" size="4643780" />
<Group pts="3186392" duration="6437" size="3002604" />
<Group pts="3192940" duration="3567" size="1699502" />
<Group pts="3196568" duration="9840" size="4286828" />
<Group pts="3206578" duration="1681" size="812111" />
<Group pts="3208288" duration="2091" size="961196" />
<Group pts="3210416" duration="9799" size="4148204" />
<Group pts="3220384" duration="9799" size="4172238" />
<Group pts="3230352" duration="9799" size="4056465" />
<Group pts="3240320" duration="9799" size="4432107" />
<Group pts="3250289" duration="2091" size="1049614" />
<Group pts="3252416" duration="9799" size="5124880" />
<Group pts="3262384" duration="9799" size="5383976" />
<Group pts="3272352" duration="1271" size="694237" />
<Group pts="3273645" duration="3895" size="2170566" />
<Group pts="3277608" duration="9799" size="4488331" />
<Group pts="3287576" duration="5084" size="2153594" />
<Group pts="3292748" duration="9840" size="4862222" />
<Group pts="3302758" duration="9840" size="5159854" />
<Group pts="3312768" duration="3280" size="1684228" />
<Group pts="3316104" duration="7257" size="3379502" />
<Group pts="3323487" duration="8118" size="4699273" />
<Group pts="3331745" duration="9840" size="5472125" />
<Group pts="3341755" duration="9840" size="5931686" />
<Group pts="3351765" duration="9840" size="5374306" />
<Group pts="3361775" duration="4920" size="2827695" />
<Group pts="3366780" duration="9840" size="4967398" />
<Group pts="3376790" duration="9840" size="4789307" />
<Group pts="3386800" duration="9840" size="4681252" />
<Group pts="3396810" duration="2870" size="1588822" />
<Group pts="3399730" duration="4920" size="1905887" />
<Group pts="3404735" duration="9840" size="5798435" />
<Group pts="3414745" duration="3895" size="2249489" />
<Group pts="3418707" duration="9758" size="4747988" />
<Group pts="3428634" duration="9840" size="5060953" />
<Group pts="3438644" duration="3075" size="1406113" />
<Group pts="3441772" duration="9799" size="4310096" />
<Group pts="3451740" duration="7093" size="3356615" />
<Group pts="3458956" duration="9840" size="4205336" />
<Group pts="3468966" duration="9840" size="4843370" />
<Group pts="3478976" duration="2009" size="904724" />
<Group pts="3481019" duration="6765" size="3024479" />
<Group pts="3487901" duration="6724" size="3145415" />
<Group pts="3494741" duration="7298" size="3186308" />
<Group pts="3502165" duration="9799" size="4415387" />
<Group pts="3512134" duration="2132" size="1027891" />
<Group pts="3514302" duration="9840" size="5029039" />
<Group pts="3524312" duration="8323" size="5242944" />
<Group pts="3532779" duration="8897" size="5248067" />
<Group pts="3541830" duration="9840" size="4930794" />
<Group pts="3551840" duration="9840" size="5366498" />
<Group pts="3561850" duration="2952" size="1702725" />
<Group pts="3564853" duration="9840" size="5997177" />
<Group pts="3574863" duration="9840" size="6037451" />
<Group pts="3584873" duration="9840" size="5759050" />
<Group pts="3594883" duration="9799" size="5971525" />
<Group pts="3604851" duration="9799" size="6019520" />
<Group pts="3614820" duration="2337" size="1398125" />
<Group pts="3617197" duration="9840" size="4482875" />
<Group pts="3627207" duration="9840" size="3872191" />
<Group pts="3637217" duration="9840" size="3571919" />
<Group pts="3647227" duration="9840" size="4165119" />
<Group pts="3657237" duration="9799" size="3832323" />
<Group pts="3667205" duration="9799" size="3675367" />
<Group pts="3677174" duration="9840" size="4205084" />
<Group pts="3687184" duration="9840" size="6299842" />
<Group pts="3697194" duration="9840" size="6912676" />
<Group pts="3707204" duration="9840" size="6932752" />
<Group pts="3717214" duration="1066" size="703121" />
<Group pts="3718298" duration="9840" size="5848915" />
<Group pts="3728308" duration="9799" size="5724522" />
<Group pts="3738276" duration="9799" size="5525675" />
<Group pts="3748245" duration="9840" size="5988586" />
<Group pts="3758255" duration="9840" size="5595856" />
<Group pts="3768265" duration="9840" size="5679914" />
<Group pts="3778275" duration="9840" size="6239956" />
<Group pts="3788285" duration="9840" size="5506957" />
<Group pts="3798295" duration="9840" size="5479789" />
<Group pts="3808305" duration="9143" size="5003829" />
<Group pts="3817605" duration="9840" size="4977086" />
<Group pts="3827615" duration="9840" size="5130220" />
<Group pts="3837625" duration="9840" size="5691642" />
<Group pts="3847635" duration="9799" size="4916513" />
<Group pts="3857604" duration="9799" size="4896492" />
<Group pts="3867572" duration="9799" size="5428702" />
<Group pts="3877540" duration="9799" size="5539116" />
<Group pts="3887509" duration="9799" size="5418643" />
<Group pts="3897477" duration="9799" size="5248070" />
<Group pts="3907445" duration="9799" size="5446896" />
<Group pts="3917414" duration="9799" size="5523679" />
<Group pts="3927382" duration="6314" size="3602885" />
<Group pts="3933805" duration="5330" size="2884508" />
<Group pts="3939227" duration="9799" size="5576160" />
<Group pts="3949195" duration="4264" size="2557981" />
<Group pts="3953533" duration="9840" size="5278533" />
<Group pts="3963543" duration="9799" size="6042926" />
<Group pts="3973511" duration="9840" size="5859622" />
<Group pts="3983521" duration="3075" size="1753388" />
<Group pts="3986649" duration="9799" size="4992969" />
<Group pts="3996618" duration="4428" size="2269174" />
<Group pts="4001122" duration="9840" size="4557922" />
<Group pts="4011132" duration="9799" size="5229225" />
<Group pts="4021100" duration="9799" size="5652262" />
<Group pts="4031069" duration="9840" size="5580912" />
<Group pts="4041079" duration="9840" size="6064306" />
<Group pts="4051089" duration="9840" size="5720772" />
<Group pts="4061099" duration="9840" size="4058099" />
<Group pts="4071109" duration="9840" size="5424637" />
<Group pts="4081119" duration="9840" size="4722603" />
<Group pts="4091129" duration="9840" size="6015102" />
<Group pts="4101139" duration="9799" size="5592486" />
<Group pts="4111107" duration="9799" size="5552141" />
<Group pts="4121075" duration="1968" size="1161963" />
<Group pts="4123077" duration="9799" size="6185498" />
<Group pts="4133046" duration="9758" size="5953339" />
<Group pts="4142972" duration="7216" size="4358923" />
<Group pts="4150313" duration="9840" size="5010631" />
<Group pts="4160323" duration="9799" size="5033584" />
<Group pts="4170291" duration="9799" size="5369431" />
<Group pts="4180259" duration="6929" size="4317905" />
<Group pts="4187308" duration="9840" size="5693246" />
<Group pts="4197318" duration="9840" size="5614340" />
<Group pts="4207328" duration="1025" size="633344" />
<Group pts="4208371" duration="9799" size="5225509" />
<Group pts="4218339" duration="9799" size="5087938" />
<Group pts="4228307" duration="9799" size="5671155" />
<Group pts="4238276" duration="2501" size="1365336" />
<Group pts="4240820" duration="9799" size="5951999" />
<Group pts="4250788" duration="9799" size="5488619" />
<Group pts="4260757" duration="9799" size="5754524" />
<Group pts="4270725" duration="9799" size="5752094" />
<Group pts="4280693" duration="9840" size="5389895" />
<Group pts="4290703" duration="2173" size="1189333" />
<Group pts="4292914" duration="9799" size="5384053" />
<Group pts="4302882" duration="2255" size="1280929" />
<Group pts="4305176" duration="9799" size="5256375" />
<Group pts="4315144" duration="9840" size="5913741" />
<Group pts="4325154" duration="9799" size="5792808" />
<Group pts="4335122" duration="9799" size="5615220" />
<Group pts="4345091" duration="9799" size="5541013" />
<Group pts="4355059" duration="9799" size="5490735" />
<Group pts="4365027" duration="9799" size="5578557" />
<Group pts="4374996" duration="2296" size="1345257" />
<Group pts="4377331" duration="9471" size="5341195" />
<Group pts="4386966" duration="9799" size="5702613" />
<Group pts="4396934" duration="2214" size="1223596" />
<Group pts="4399186" duration="9799" size="5234896" />
<Group pts="4409155" duration="1148" size="729699" />
<Group pts="4410323" duration="9799" size="5354078" />
<Group pts="4420291" duration="3772" size="2102298" />
<Group pts="4424128" duration="9799" size="5341081" />
<Group pts="4434096" duration="3239" size="1767583" />
<Group pts="4437391" duration="3731" size="2107075" />
<Group pts="4441187" duration="9799" size="5239339" />
<Group pts="4451155" duration="9799" size="5663979" />
<Group pts="4461123" duration="1722" size="1047169" />
<Group pts="4462875" duration="9758" size="5038793" />
<Group pts="4472802" duration="9840" size="5636413" />
<Group pts="4482812" duration="9799" size="5344921" />
<Group pts="4492780" duration="9799" size="4700715" />
<Group pts="4502748" duration="9840" size="4604854" />
<Group pts="4512758" duration="9840" size="3729381" />
<Group pts="4522768" duration="9799" size="3754658" />
<Group pts="4532737" duration="3936" size="1633776" />
<Group pts="4536741" duration="9840" size="3704367" />
<Group pts="4546751" duration="9799" size="4116972" />
<Group pts="4556719" duration="9799" size="3818309" />
<Group pts="4566687" duration="2829" size="1193219" />
<Group pts="4569565" duration="9799" size="3389292" />
<Group pts="4579533" duration="9799" size="3629341" />
<Group pts="4589502" duration="5617" size="2024613" />
<Group pts="4595216" duration="9799" size="3421613" />
<Group pts="4605184" duration="9840" size="3862248" />
<Group pts="4615194" duration="9758" size="3566285" />
<Group pts="4625121" duration="2911" size="1117004" />
<Group pts="4628082" duration="9840" size="4439045" />
<Group pts="4638092" duration="9799" size="4751082" />
<Group pts="4648060" duration="9840" size="5488876" />
<Group pts="4658070" duration="9799" size="5439154" />
<Group pts="4668038" duration="9840" size="6348027" />
<Group pts="4678048" duration="9840" size="6375263" />
<Group pts="4688058" duration="9758" size="6276342" />
<Group pts="4697985" duration="9840" size="5934039" />
<Group pts="4707995" duration="9799" size="5782642" />
<Group pts="4717963" duration="4182" size="2661768" />
<Group pts="4722218" duration="9799" size="6475567" />
<Group pts="4732186" duration="1189" size="892140" />
<Group pts="4733395" duration="2419" size="1492178" />
<Group pts="4735856" duration="2460" size="1710284" />
<Group pts="4738359" duration="3854" size="2442279" />
<Group pts="4742279" duration="5576" size="3589318" />
<Group pts="4747952" duration="9799" size="6121225" />
<Group pts="4757920" duration="5576" size="3259839" />
<Group pts="4763592" duration="7011" size="4012076" />
<Group pts="4770724" duration="9840" size="5693587" />
<Group pts="4780734" duration="9799" size="5420853" />
<Group pts="4790703" duration="9799" size="4968728" />
<Group pts="4800671" duration="9799" size="4862533" />
<Group pts="4810639" duration="9799" size="4907767" />
<Group pts="4820607" duration="9840" size="2646147" />
<Group pts="4830617" duration="9840" size="4821738" />
<Group pts="4840627" duration="9799" size="5064584" />
<Group pts="4850596" duration="9799" size="5401806" />
<Group pts="4860564" duration="9799" size="5765882" />
<Group pts="4870532" duration="9799" size="5638271" />
<Group pts="4880501" duration="9799" size="5857052" />
<Group pts="4890469" duration="9799" size="6135541" />
<Group pts="4900437" duration="9799" size="5961253" />
<Group pts="4910406" duration="9799" size="5947216" />
<Group pts="4920374" duration="9799" size="6153375" />
<Group pts="4930342" duration="9799" size="6297479" />
<Group pts="4940310" duration="9799" size="5723869" />
<Group pts="4950279" duration="1599" size="958468" />
<Group pts="4951905" duration="9799" size="5678293" />
<Group pts="4961874" duration="2378" size="1519027" />
<Group pts="4964293" duration="9840" size="6377792" />
<Group pts="4974303" duration="9799" size="5798065" />
<Group pts="4984271" duration="9840" size="5642915" />
<Group pts="4994281" duration="9799" size="5269874" />
<Group pts="5004249" duration="9799" size="4789989" />
<Group pts="5014218" duration="1107" size="544635" />
<Group pts="5015344" duration="9840" size="4315394" />
<Group pts="5025354" duration="2583" size="1170821" />
<Group pts="5027981" duration="4469" size="1924369" />
<Group pts="5032528" duration="9799" size="4257467" />
<Group pts="5042496" duration="9799" size="4298094" />
<Group pts="5052464" duration="9799" size="4416483" />
<Group pts="5062432" duration="1230" size="597033" />
<Group pts="5063684" duration="9799" size="4492337" />
<Group pts="5073652" duration="9799" size="5076944" />
<Group pts="5083620" duration="3526" size="1833298" />
<Group pts="5087207" duration="9840" size="5323996" />
<Group pts="5097217" duration="9840" size="5329762" />
<Group pts="5107227" duration="1804" size="1026224" />
<Group pts="5109062" duration="5494" size="2697720" />
<Group pts="5114651" duration="9799" size="4782737" />
<Group pts="5124620" duration="2501" size="1223586" />
<Group pts="5127164" duration="9799" size="4941019" />
<Group pts="5137132" duration="9799" size="4757411" />
<Group pts="5147100" duration="5084" size="2650101" />
<Group pts="5152272" duration="9799" size="5009704" />
<Group pts="5162240" duration="9799" size="4656905" />
<Group pts="5172209" duration="9799" size="4872328" />
<Group pts="5182177" duration="9840" size="4679372" />
<Group pts="5192187" duration="1189" size="582758" />
<Group pts="5193397" duration="9799" size="4698514" />
<Group pts="5203365" duration="9799" size="5165408" />
<Group pts="5213333" duration="9799" size="5368925" />
<Group pts="5223301" duration="9799" size="5559019" />
<Group pts="5233270" duration="9799" size="5533881" />
<Group pts="5243238" duration="9799" size="5489494" />
<Group pts="5253206" duration="9799" size="5419822" />
<Group pts="5263175" duration="9799" size="5239441" />
<Group pts="5273143" duration="9799" size="5338552" />
<Group pts="5283111" duration="9799" size="5572569" />
<Group pts="5293079" duration="9799" size="5890763" />
<Group pts="5303048" duration="9799" size="5795138" />
<Group pts="5313016" duration="9799" size="5713974" />
<Group pts="5322984" duration="9799" size="5739355" />
<Group pts="5332953" duration="9799" size="5369212" />
<Group pts="5342921" duration="9799" size="5233560" />
<Group pts="5352889" duration="1353" size="720172" />
<Group pts="5354266" duration="7872" size="3670779" />
<Group pts="5362274" duration="9840" size="4625431" />
<Group pts="5372284" duration="9799" size="4842494" />
<Group pts="5382252" duration="9799" size="5139867" />
<Group pts="5392220" duration="9799" size="5391034" />
<Group pts="5402188" duration="9799" size="4918843" />
<Group pts="5412157" duration="9799" size="4551552" />
<Group pts="5422125" duration="9799" size="4531074" />
<Group pts="5432093" duration="9840" size="4977200" />
<Group pts="5442103" duration="4510" size="2193640" />
<Group pts="5446691" duration="9799" size="4485169" />
<Group pts="5456660" duration="9799" size="4815606" />
<Group pts="5466628" duration="1927" size="990273" />
<Group pts="5468588" duration="9799" size="4693663" />
<Group pts="5478556" duration="4633" size="2198725" />
<Group pts="5483269" duration="9799" size="4637986" />
<Group pts="5493238" duration="9799" size="5204834" />
<Group pts="5503206" duration="9799" size="5430719" />
<Group pts="5513174" duration="4551" size="2525542" />
<Group pts="5517804" duration="9799" size="5134444" />
<Group pts="5527772" duration="9799" size="4276066" />
<Group pts="5537741" duration="3321" size="1480793" />
<Group pts="5541119" duration="9799" size="4696137" />
<Group pts="5551087" duration="9799" size="4815547" />
<Group pts="5561056" duration="9799" size="4950490" />
<Group pts="5571024" duration="9799" size="5098064" />
<Group pts="5580992" duration="9799" size="4983473" />
<Group pts="5590960" duration="9799" size="5013768" />
<Group pts="5600929" duration="9799" size="5531861" />
<Group pts="5610897" duration="3813" size="1967231" />
<Group pts="5614776" duration="9840" size="4441015" />
<Group pts="5624786" duration="7216" size="3020265" />
<Group pts="5632127" duration="9840" size="3084307" />
<Group pts="5642137" duration="2665" size="841666" />
<Group pts="5644848" duration="9840" size="3195739" />
<Group pts="5654858" duration="4879" size="1390678" />
<Group pts="5659821" duration="9840" size="3018597" />
<Group pts="5669831" duration="7872" size="2726670" />
<Group pts="5677839" duration="9799" size="2793680" />
<Group pts="5687807" duration="2583" size="1022385" />
<Group pts="5690435" duration="9840" size="475996" />
<Group pts="5700445" duration="9840" size="54730" />
<Group pts="5710455" duration="9840" size="65271" />
<Group pts="5720465" duration="9840" size="63166" />
<Group pts="5730475" duration="9840" size="49114" />
<Group pts="5740485" duration="9840" size="21833" />
<Group pts="5750495" duration="9840" size="43564" />
<Group pts="5760505" duration="9840" size="61946" />
<Group pts="5770515" duration="9840" size="70135" />
<Group pts="5780525" duration="9840" size="68903" />
<Group pts="5790535" duration="9840" size="63354" />
<Group pts="5800545" duration="9840" size="57474" />
<Group pts="5810555" duration="9840" size="48911" />
<Group pts="5820565" duration="5781" size="14426" />
<Group pts="5826446" duration="9840" size="21508" />
<Group pts="5836456" duration="9840" size="52899" />
<Group pts="5846466" duration="9840" size="60536" />
<Group pts="5856476" duration="9840" size="58737" />
<Group pts="5866486" duration="5535" size="15953" />
<Group pts="5872116" duration="9840" size="75003" />
<Group pts="5882126" duration="4715" size="13269" />
</VideoStream>
